phables/__init__.py
phables/__main__.py
phables/phables.CITATION
phables/phables.LICENSE
phables/phables.VERSION
phables/config/config.yaml
phables/config/databases.yaml
phables/test_data/assembly_graph.gfa
phables/test_data/edge_coverages.tsv
phables/test_data/edges.fasta.hmmout
phables/test_data/junction_pe_coverage.pickle
phables/test_data/phrogs_annotations.tsv
phables/workflow/install.smk
phables/workflow/phables.smk
phables/workflow/test_phables.smk
phables/workflow/envs/curl.yaml
phables/workflow/envs/koverage.yaml
phables/workflow/envs/mapping.yaml
phables/workflow/envs/mmseqs.yaml
phables/workflow/envs/phables.yaml
phables/workflow/envs/phylotree.yaml
phables/workflow/envs/smg.yaml
phables/workflow/rules/00_database_preflight.smk
phables/workflow/rules/02_phables_preflight.smk
phables/workflow/rules/02_phables_targets.smk
phables/workflow/rules/03_test_preflight.smk
phables/workflow/rules/03_test_targets.smk
phables/workflow/rules/coverage.smk
phables/workflow/rules/genes.smk
phables/workflow/rules/gfa2fasta.smk
phables/workflow/rules/phables.smk
phables/workflow/rules/phylotree.smk
phables/workflow/rules/postprocess.smk
phables/workflow/scripts/combine_cov.py
phables/workflow/scripts/format_koverage_results.py
phables/workflow/scripts/gfa2fasta.py
phables/workflow/scripts/phables.py
phables/workflow/scripts/phylotree.py
phables/workflow/scripts/phables_utils/FD_Inexact.py
phables/workflow/scripts/phables_utils/__init__.py
phables/workflow/scripts/phables_utils/component_utils.py
phables/workflow/scripts/phables_utils/coverage_utils.py
phables/workflow/scripts/phables_utils/edge_graph_utils.py
phables/workflow/scripts/phables_utils/flow_utils.py
phables/workflow/scripts/phables_utils/gene_utils.py
phables/workflow/scripts/phables_utils/genome_utils.py
phables/workflow/scripts/phables_utils/long_utils.py
phables/workflow/scripts/phables_utils/output_utils.py
phables/workflow/scripts/phables_utils/short_utils.py
phables-1.5.0.dist-info/licenses/LICENSE
phables-1.5.0.dist-info/METADATA
phables-1.5.0.dist-info/WHEEL
phables-1.5.0.dist-info/entry_points.txt
phables-1.5.0.dist-info/top_level.txt
phables-1.5.0.dist-info/RECORD
