Metadata-Version: 2.4
Name: phables
Version: 1.5.0
Summary: Phables: from fragmented assemblies to high-quality bacteriophage genomes
Home-page: https://github.com/Vini2/phables
Author: Vijini Mallawaarachchi
Author-email: viji.mallawaarachchi@gmail.com
Classifier: Development Status :: 5 - Production/Stable
Classifier: Programming Language :: Python :: 3
Classifier: License :: OSI Approved :: MIT License
Classifier: Natural Language :: English
Classifier: Topic :: Scientific/Engineering :: Bio-Informatics
Classifier: Operating System :: MacOS
Classifier: Operating System :: POSIX
Requires-Python: >=3.9, <3.11
License-File: LICENSE
Requires-Dist: snakemake>=7.14.0
Requires-Dist: pyyaml>=6.0
Requires-Dist: click>=8.1.3
Requires-Dist: metasnek>=0.0.5
Requires-Dist: snaketool-utils>=0.0.4
Dynamic: author
Dynamic: author-email
Dynamic: classifier
Dynamic: description
Dynamic: description-content-type
Dynamic: home-page
Dynamic: license-file
Dynamic: requires-dist
Dynamic: requires-python
Dynamic: summary
